pyeq3/IModel.py
pyeq3/Model_2D_BaseClass.py
pyeq3/Model_3D_BaseClass.py
pyeq3/PolyFunctions.py
pyeq3/__init__.py
pyeq3/version.py
pyeq3/DataCache/DataCache.py
pyeq3/DataCache/DataCacheFunctions.py
pyeq3/DataCache/__init__.py
pyeq3/ExtendedVersionHandlers/ExtendedVersionHandler_Default.py
pyeq3/ExtendedVersionHandlers/ExtendedVersionHandler_ExponentialDecay.py
pyeq3/ExtendedVersionHandlers/ExtendedVersionHandler_ExponentialDecayAndOffset.py
pyeq3/ExtendedVersionHandlers/ExtendedVersionHandler_ExponentialGrowth.py
pyeq3/ExtendedVersionHandlers/ExtendedVersionHandler_ExponentialGrowthAndOffset.py
pyeq3/ExtendedVersionHandlers/ExtendedVersionHandler_Inverse.py
pyeq3/ExtendedVersionHandlers/ExtendedVersionHandler_InverseWithOffset.py
pyeq3/ExtendedVersionHandlers/ExtendedVersionHandler_LinearDecay.py
pyeq3/ExtendedVersionHandlers/ExtendedVersionHandler_LinearDecayAndOffset.py
pyeq3/ExtendedVersionHandlers/ExtendedVersionHandler_LinearGrowth.py
pyeq3/ExtendedVersionHandlers/ExtendedVersionHandler_LinearGrowthAndOffset.py
pyeq3/ExtendedVersionHandlers/ExtendedVersionHandler_Offset.py
pyeq3/ExtendedVersionHandlers/ExtendedVersionHandler_PlusLine.py
pyeq3/ExtendedVersionHandlers/ExtendedVersionHandler_PlusPlane.py
pyeq3/ExtendedVersionHandlers/ExtendedVersionHandler_Reciprocal.py
pyeq3/ExtendedVersionHandlers/ExtendedVersionHandler_ReciprocalWithOffset.py
pyeq3/ExtendedVersionHandlers/IExtendedVersionHandler.py
pyeq3/ExtendedVersionHandlers/__init__.py
pyeq3/Graphics/Graphics2D.py
pyeq3/Graphics/__init__.py
pyeq3/Models_2D/Astrophysics.py
pyeq3/Models_2D/BioScience.py
pyeq3/Models_2D/BurkardtCollectionBased.py
pyeq3/Models_2D/Engineering.py
pyeq3/Models_2D/Exponential.py
pyeq3/Models_2D/FourierSeries.py
pyeq3/Models_2D/LegendrePolynomial.py
pyeq3/Models_2D/Logarithmic.py
pyeq3/Models_2D/Miscellaneous.py
pyeq3/Models_2D/NIST.py
pyeq3/Models_2D/Optical.py
pyeq3/Models_2D/Peak.py
pyeq3/Models_2D/Polyfunctional.py
pyeq3/Models_2D/Polynomial.py
pyeq3/Models_2D/Power.py
pyeq3-12.6.1.dist-info/METADATA
pyeq3-12.6.1.dist-info/WHEEL
pyeq3-12.6.1.dist-info/top_level.txt
pyeq3-12.6.1.dist-info/RECORD
