Metadata-Version: 2.1
Name: pyeq3
Version: 12.6.1
Summary: An equation, curve and surface fitting library
Home-page: https://github.com/equations-project/pyeq3
Author: James Phillips, Robert Myhill
Author-email: bob.myhill@bristol.ac.uk
License: BSD
Keywords: curve,surface,fitting
Classifier: License :: OSI Approved :: BSD License
Classifier: Development Status :: 6 - Mature
Classifier: Intended Audience :: Developers
Classifier: Topic :: Scientific/Engineering :: Mathematics
Classifier: Programming Language :: Python :: 3.7
Classifier: Programming Language :: Python :: 3.8
Classifier: Programming Language :: Python :: 3.9
Classifier: Programming Language :: Python :: 3.10
Requires-Dist: numpy
Requires-Dist: matplotlib
Requires-Dist: scipy
